kaptive/__init__.py
kaptive/__main__.py
kaptive/alignment.py
kaptive/assembly.py
kaptive/database.py
kaptive/log.py
kaptive/typing.py
kaptive/utils.py
kaptive/version.py
kaptive-3.1.0.dist-info/licenses/LICENSE
reference_database/Acinetobacter_baumannii_OC_locus_primary_reference.gbk
reference_database/Acinetobacter_baumannii_k_locus_primary_reference.gbk
reference_database/Acinetobacter_baumannii_k_locus_primary_reference.logic
reference_database/Klebsiella_k_locus_primary_reference.gbk
reference_database/Klebsiella_k_locus_primary_reference.logic
reference_database/Klebsiella_o_locus_primary_reference.gbk
reference_database/Klebsiella_o_locus_primary_reference.logic
kaptive-3.1.0.dist-info/METADATA
kaptive-3.1.0.dist-info/WHEEL
kaptive-3.1.0.dist-info/entry_points.txt
kaptive-3.1.0.dist-info/top_level.txt
kaptive-3.1.0.dist-info/RECORD
