Metadata-Version: 2.4
Name: kaptive
Version: 3.1.0
Summary: In silico serotyping
Author-email: Tom Stanton <tomdstanton@gmail.com>
License:                     GNU GENERAL PUBLIC LICENSE
Keywords: bioinformatics,serotyping,microbiology
Classifier: Environment :: Console
Classifier: Operating System :: OS Independent
Classifier: License :: OSI Approved :: GNU General Public License v3 (GPLv3)
Classifier: Topic :: Scientific/Engineering :: Bio-Informatics
Classifier: Topic :: Scientific/Engineering :: Medical Science Apps.
Classifier: Programming Language :: Python :: 3.9
Classifier: Programming Language :: Python :: 3.10
Classifier: Programming Language :: Python :: 3.11
Classifier: Programming Language :: Python :: 3.12
Requires-Python: >=3.9
License-File: LICENSE
Requires-Dist: biopython
Requires-Dist: numpy
Requires-Dist: matplotlib
Requires-Dist: dna_features_viewer
Dynamic: license-file
